ipclog/__init__.py
ipclog/ipc_server.py
ipclog/logger.py
ipclog-0.0.1.dist-info/LICENSE
ipclog-0.0.1.dist-info/METADATA
ipclog-0.0.1.dist-info/WHEEL
ipclog-0.0.1.dist-info/top_level.txt
ipclog-0.0.1.dist-info/RECORD
