Metadata-Version: 2.1
Name: ipclog
Version: 0.0.1
Summary: Non-blocking consumption of multi-process log messages
Author-email: vonv <ars.von.roseregen@gmail.com>
Project-URL: Homepage, https://github.com/vonsago/ipclog
Project-URL: Bug Tracker, https://github.com/vonsago/ipclog/issues
Classifier: Programming Language :: Python :: 3
Classifier: License :: OSI Approved :: MIT License
Classifier: Operating System :: OS Independent
Requires-Python: >=3.7
License-File: LICENSE
